ParticleRigidityCalculationTools.py
ParticleRigidityCalculationTools-1.5.17.dist-info/LICENSE
ParticleRigidityCalculationTools-1.5.17.dist-info/METADATA
ParticleRigidityCalculationTools-1.5.17.dist-info/WHEEL
ParticleRigidityCalculationTools-1.5.17.dist-info/top_level.txt
ParticleRigidityCalculationTools-1.5.17.dist-info/RECORD
