Metadata-Version: 2.2
Name: ParticleRigidityCalculationTools
Version: 1.5.17
Summary: Python library containing tools for dealing with conversions between particle energy and rigidity
Home-page: https://github.com/ssc-maire/ParticleRigidityCalculationTools
Author: Space Environment and Protection Group, University of Surrey
License: CC BY-NC-SA 4.0
Keywords: space physics earth geomagnetic rigidity magnetocosmics
License-File: LICENSE
Requires-Dist: numpy>=1.23.1
Requires-Dist: pandas>=1.4.3
Requires-Dist: setuptools>=45.2.0
Dynamic: author
Dynamic: description
Dynamic: description-content-type
Dynamic: home-page
Dynamic: keywords
Dynamic: license
Dynamic: requires-dist
Dynamic: summary
